Metadata-Version: 2.1
Name: odoo14-addon-ecommerce_connector
Version: 14.0.3.0.1
Summary: General E-Commerce Integration
Author: Sygel
License: AGPL-3
Classifier: Programming Language :: Python
Classifier: Framework :: Odoo
Classifier: Framework :: Odoo :: 14.0
Classifier: License :: OSI Approved :: GNU Affero General Public License v3
Requires-Python: >=3.6
Requires-Dist: odoo14-addon-account-fiscal-position-partner-type
Requires-Dist: odoo14-addon-account-payment-mode
Requires-Dist: odoo14-addon-account-payment-sale
Requires-Dist: odoo<14.1dev,>=14.0a
